fastapi_easy_cache/__init__.py
fastapi_easy_cache/fastapiCache.py
fastapi_easy_cache-1.0.2.dist-info/METADATA
fastapi_easy_cache-1.0.2.dist-info/WHEEL
fastapi_easy_cache-1.0.2.dist-info/RECORD
