Metadata-Version: 2.1
Name: fastapi-easy-cache
Version: 1.0.2
Summary: 
Author: DrEgg
Author-email: dev@dregg.me
Requires-Python: >=3.11,<4.0
Classifier: Programming Language :: Python :: 3
Classifier: Programming Language :: Python :: 3.11
Classifier: Programming Language :: Python :: 3.12
Requires-Dist: sqlalchemy (>=2.0.25,<3.0.0)
